RefactoringIdioms/CodeInfo.py
RefactoringIdioms/__init__.py
RefactoringIdioms/__main__.py
RefactoringIdioms/complicated_code_util.py
RefactoringIdioms/file copy.py
RefactoringIdioms/file.py
RefactoringIdioms/file_copy_2.py
RefactoringIdioms/main.py
RefactoringIdioms/util.py
RefactoringIdioms/RefactoringIdiomsOutputdir/file.py
RefactoringIdioms/extract_simp_cmpl_data/__init__.py
RefactoringIdioms/extract_simp_cmpl_data/ast_util.py
RefactoringIdioms/extract_simp_cmpl_data/extract_compli_truth_value_test_code.py
RefactoringIdioms/extract_transform_complicate_code_new/__init__.py
RefactoringIdioms/extract_transform_complicate_code_new/count_compl_count.py
RefactoringIdioms/extract_transform_complicate_code_new/extract_compli_multiple_assign_code_improve_complete_improve.py
RefactoringIdioms/extract_transform_complicate_code_new/extract_compli_truth_value_test_code.py
RefactoringIdioms/extract_transform_complicate_code_new/extract_compli_truth_value_test_code_remove_is_isnot.py
RefactoringIdioms/extract_transform_complicate_code_new/extract_compli_var_unpack_for_target_improve.py
RefactoringIdioms/extract_transform_complicate_code_new/extract_compli_var_unpack_for_target_improve_new.py
RefactoringIdioms/extract_transform_complicate_code_new/extract_compli_var_unpack_star_call_improve.py
RefactoringIdioms/extract_transform_complicate_code_new/extract_compli_var_unpack_star_call_improve_fix_negtive.py
RefactoringIdioms/extract_transform_complicate_code_new/extract_compli_var_unpack_star_call_improve_strict.py
RefactoringIdioms/extract_transform_complicate_code_new/transform_chained_comparison_compli_to_simple.py
RefactoringIdioms/extract_transform_complicate_code_new/transform_for_else_compli_to_simple_improve.py
RefactoringIdioms/extract_transform_complicate_code_new/transform_for_else_compli_to_simple_improve_copy.py
RefactoringIdioms/extract_transform_complicate_code_new/transform_for_else_compli_to_simple_improve_copy_result_csv.py
RefactoringIdioms-0.0.11.dist-info/LICENSE
RefactoringIdioms-0.0.11.dist-info/METADATA
RefactoringIdioms-0.0.11.dist-info/WHEEL
RefactoringIdioms-0.0.11.dist-info/entry_points.txt
RefactoringIdioms-0.0.11.dist-info/top_level.txt
RefactoringIdioms-0.0.11.dist-info/RECORD
